clint_utilities/__init__.py
python_clint_utilities-1.2.2.dist-info/AUTHORS
python_clint_utilities-1.2.2.dist-info/LICENSE.txt
python_clint_utilities-1.2.2.dist-info/METADATA
python_clint_utilities-1.2.2.dist-info/WHEEL
python_clint_utilities-1.2.2.dist-info/top_level.txt
python_clint_utilities-1.2.2.dist-info/RECORD
